cached_path/__init__.py
cached_path/_cached_path.py
cached_path/bytes_range.py
cached_path/cache_file.py
cached_path/common.py
cached_path/file_lock.py
cached_path/meta.py
cached_path/progress.py
cached_path/testing.py
cached_path/util.py
cached_path/version.py
cached_path/schemes/__init__.py
cached_path/schemes/beaker.py
cached_path/schemes/beaker_v1.py
cached_path/schemes/gs.py
cached_path/schemes/hf.py
cached_path/schemes/http.py
cached_path/schemes/r2.py
cached_path/schemes/s3.py
cached_path/schemes/scheme_client.py
cached_path-1.8.1.dist-info/licenses/LICENSE
cached_path-1.8.1.dist-info/METADATA
cached_path-1.8.1.dist-info/WHEEL
cached_path-1.8.1.dist-info/top_level.txt
cached_path-1.8.1.dist-info/RECORD
