Metadata-Version: 2.4
Name: cached_path
Version: 1.8.1
Summary: A file utility for accessing both local and remote files through a unified interface
Author-email: Allen Institute for Artificial Intelligence <contact@allenai.org>
License:                                  Apache License
Project-URL: Homepage, https://github.com/allenai/cached_path
Project-URL: Repository, https://github.com/allenai/cached_path
Project-URL: Changelog, https://github.com/allenai/cached_path/blob/main/CHANGELOG.md
Project-URL: Documentation, https://cached-path.readthedocs.io/
Classifier: Intended Audience :: Science/Research
Classifier: License :: OSI Approved :: Apache Software License
Classifier: Programming Language :: Python :: 3
Classifier: Topic :: Scientific/Engineering :: Artificial Intelligence
Requires-Python: >=3.9
License-File: LICENSE
Requires-Dist: requests
Requires-Dist: rich<14.0,>=12.1
Requires-Dist: filelock<4.0,>=3.4
Requires-Dist: boto3<2.0,>=1.0
Requires-Dist: google-cloud-storage<4.0,>=1.32.0
Requires-Dist: huggingface-hub<2.0,>=0.8.1
Requires-Dist: packaging
Provides-Extra: dev
Requires-Dist: beaker-py<3.0; extra == "dev"
Requires-Dist: ruff; extra == "dev"
Requires-Dist: mypy<2.0,>=1.6.0; extra == "dev"
Requires-Dist: black<25.0,>=23.1.0; extra == "dev"
Requires-Dist: isort<6.0,>=5.12.0; extra == "dev"
Requires-Dist: pytest; extra == "dev"
Requires-Dist: flaky; extra == "dev"
Requires-Dist: twine>=1.11.0; extra == "dev"
Requires-Dist: setuptools; extra == "dev"
Requires-Dist: wheel; extra == "dev"
Requires-Dist: build; extra == "dev"
Requires-Dist: responses==0.21.0; extra == "dev"
Requires-Dist: types-requests; extra == "dev"
Requires-Dist: Sphinx<8.0,>=6.0; extra == "dev"
Requires-Dist: furo==2024.1.29; extra == "dev"
Requires-Dist: myst-parser<3.0,>=1.0.0; extra == "dev"
Requires-Dist: sphinx-copybutton==0.5.2; extra == "dev"
Requires-Dist: sphinx-autobuild==2021.3.14; extra == "dev"
Requires-Dist: sphinx-autodoc-typehints; extra == "dev"
Dynamic: license-file
